[
  {
    "_id": "5907da2898ef9b8a04d13d5a",
    "age": 35,
    "name": "Kristi Todd",
    "email": "kristitodd@cipromox.com",
    "password": "{f4542db9ba30f7958ae42c113dd87ad21fb2eddb}"
  },
  {
    "_id": "5907da2877e164f30dd75671",
    "age": 27,
    "name": "Saundra Christensen",
    "email": "saundrachristensen@cipromox.com",
    "password": "{f4542db9ba30f7958ae42c113dd87ad21fb2eddb}"
  },
  {
    "_id": "5907da28dc30e2b5cbde118f",
    "age": 23,
    "name": "Burgess Marshall",
    "email": "burgessmarshall@cipromox.com",
    "password": "{f4542db9ba30f7958ae42c113dd87ad21fb2eddb}"
  },
  {
    "_id": "5907da2847139b9548a4feba",
    "age": 31,
    "name": "Gayle Carey",
    "email": "gaylecarey@cipromox.com",
    "password": "{f4542db9ba30f7958ae42c113dd87ad21fb2eddb}"
  },
  {
    "_id": "5907da286d15c8ba09db3fc2",
    "age": 26,
    "name": "Elma Shepherd",
    "email": "elmashepherd@cipromox.com",
    "password": "{f4542db9ba30f7958ae42c113dd87ad21fb2eddb}"
  },
  {
    "_id": "5907da286afd5652cf53f94e",
    "age": 22,
    "name": "Berger Jenkins",
    "email": "bergerjenkins@cipromox.com",
    "password": "{f4542db9ba30f7958ae42c113dd87ad21fb2eddb}"
  },
  {
    "_id": "5907da282f89a07eba27ef20",
    "age": 36,
    "name": "Latasha Mooney",
    "email": "latashamooney@cipromox.com",
    "password": "{f4542db9ba30f7958ae42c113dd87ad21fb2eddb}"
  },
  {
    "_id": "5907da2829a4c2c79ab7a2e4",
    "age": 22,
    "name": "Valeria Vaughn",
    "email": "valeriavaughn@cipromox.com",
    "password": "{f4542db9ba30f7958ae42c113dd87ad21fb2eddb}"
  },
  {
    "_id": "5907da286a5f1bd4a0a7c03c",
    "age": 35,
    "name": "Stuart Montoya",
    "email": "stuartmontoya@cipromox.com",
    "password": "{f4542db9ba30f7958ae42c113dd87ad21fb2eddb}"
  },
  {
    "_id": "5907da28416c92b5d1ce723c",
    "age": 23,
    "name": "Lester Hendrix",
    "email": "lesterhendrix@cipromox.com",
    "password": "{f4542db9ba30f7958ae42c113dd87ad21fb2eddb}"
  }
]
